cftcli/attach.py
cftcli/codebuild.py
cftcli/common.py
cftcli/deploy.py
cftcli/destroy.py
cftcli/detail.py
cftcli/list.py
cftcli/list_pipelines.py
cftcli/lock.py
cftcli/policy.py
cftcli/unlock.py
cftcli-2.8.1.dist-info/METADATA
cftcli-2.8.1.dist-info/WHEEL
cftcli-2.8.1.dist-info/entry_points.txt
cftcli-2.8.1.dist-info/top_level.txt
cftcli-2.8.1.dist-info/RECORD
