Metadata-Version: 2.1
Name: cftcli
Version: 2.8.1
Summary: CloudFormation Cli
Home-page: https://github.com/tmb28054/cftcli
Author: Topaz Bott
Author-email: topaz@topazhome.net
License: Apache License 2.0
Classifier: Development Status :: 5 - Production/Stable
Classifier: Intended Audience :: Developers
Classifier: Natural Language :: English
Classifier: Programming Language :: Python
Classifier: Programming Language :: Python :: 3.8
Classifier: Programming Language :: Python :: 3.9
Classifier: Programming Language :: Python :: 3.10
Classifier: Programming Language :: Python :: 3.11
Classifier: Programming Language :: Python :: 3.12
Classifier: Programming Language :: Python :: 3.13
Classifier: Programming Language :: Python :: 3.14
Requires-Dist: boto3
Requires-Dist: halo
Requires-Dist: termcolor
Requires-Dist: tabulate
